jaccard_index/__init__.py
jaccard_index/jaccard.py
jaccard_index-0.0.3.dist-info/METADATA
jaccard_index-0.0.3.dist-info/RECORD
jaccard_index-0.0.3.dist-info/WHEEL
jaccard_index-0.0.3.dist-info/top_level.txt
