Metadata-Version: 2.1
Name: jaccard-index
Version: 0.0.3
Summary: Jaccard Index for Two Strings
Home-page: https://github.com/aniruddhadave/jaccard_index
Author: Aniruddha Dave
Author-email: aniruddhadave@gmail.com
License: UNKNOWN
Platform: UNKNOWN
Classifier: Programming Language :: Python :: 3
Classifier: License :: OSI Approved :: MIT License
Classifier: Operating System :: OS Independent
